<annotation verified="yes">
  <folder>images</folder>
  <filename>hit_000084.png</filename>
  <path>C:\Users\Bence\Diplomamunka\YOLO3\test\kettes</path>
  <source>
    <database>Generator script</database>
  </source>
  <size>
    <width>600</width>
    <height>600</height>
    <depth>3</depth>
  </size>
  <segmented>0</segmented>
  <object>
    <name>Hit</name>
    <pose>Unspecified</pose>
    <truncated>0</truncated>
    <difficult>0</difficult>
    <bndbox>
      <xmin>24.490000000000002</xmin>
      <ymin>486.49</ymin>
      <xmax>51.51</xmax>
      <ymax>51.51</ymax>
    </bndbox>
  </object>
  <object>
    <name>Hit</name>
    <pose>Unspecified</pose>
    <truncated>0</truncated>
    <difficult>0</difficult>
    <bndbox>
      <xmin>321.74</xmin>
      <ymin>196.74</ymin>
      <xmax>330.26</xmax>
      <ymax>330.26</ymax>
    </bndbox>
  </object>
  <object>
    <name>Hit</name>
    <pose>Unspecified</pose>
    <truncated>0</truncated>
    <difficult>0</difficult>
    <bndbox>
      <xmin>463.94</xmin>
      <ymin>502.94</ymin>
      <xmax>478.06</xmax>
      <ymax>478.06</ymax>
    </bndbox>
  </object>
  <object>
    <name>Hit</name>
    <pose>Unspecified</pose>
    <truncated>0</truncated>
    <difficult>0</difficult>
    <bndbox>
      <xmin>374.99</xmin>
      <ymin>152.99</ymin>
      <xmax>375.01</xmax>
      <ymax>375.01</ymax>
    </bndbox>
  </object>
  <object>
    <name>Hit</name>
    <pose>Unspecified</pose>
    <truncated>0</truncated>
    <difficult>0</difficult>
    <bndbox>
      <xmin>555.99</xmin>
      <ymin>265.99</ymin>
      <xmax>558.01</xmax>
      <ymax>558.01</ymax>
    </bndbox>
  </object>
  <object>
    <name>Hit</name>
    <pose>Unspecified</pose>
    <truncated>0</truncated>
    <difficult>0</difficult>
    <bndbox>
      <xmin>334.49</xmin>
      <ymin>220.49</ymin>
      <xmax>341.51</xmax>
      <ymax>341.51</ymax>
    </bndbox>
  </object>
  <object>
    <name>Hit</name>
    <pose>Unspecified</pose>
    <truncated>0</truncated>
    <difficult>0</difficult>
    <bndbox>
      <xmin>118.73</xmin>
      <ymin>474.73</ymin>
      <xmax>137.27</xmax>
      <ymax>137.27</ymax>
    </bndbox>
  </object>
  <object>
    <name>Hit</name>
    <pose>Unspecified</pose>
    <truncated>0</truncated>
    <difficult>0</difficult>
    <bndbox>
      <xmin>146.51</xmin>
      <ymin>41.51</ymin>
      <xmax>157.49</xmax>
      <ymax>157.49</ymax>
    </bndbox>
  </object>
  <object>
    <name>Hit</name>
    <pose>Unspecified</pose>
    <truncated>0</truncated>
    <difficult>0</difficult>
    <bndbox>
      <xmin>508.43</xmin>
      <ymin>538.43</ymin>
      <xmax>513.57</xmax>
      <ymax>513.57</ymax>
    </bndbox>
  </object>
  <object>
    <name>Hit</name>
    <pose>Unspecified</pose>
    <truncated>0</truncated>
    <difficult>0</difficult>
    <bndbox>
      <xmin>11.43</xmin>
      <ymin>246.43</ymin>
      <xmax>12.57</xmax>
      <ymax>12.57</ymax>
    </bndbox>
  </object>
</annotation>
