<annotation verified="yes">
  <folder>images</folder>
  <filename>hit_000109.png</filename>
  <path>C:\Users\Bence\Diplomamunka\YOLO3\test\kettes</path>
  <source>
    <database>Generator script</database>
  </source>
  <size>
    <width>600</width>
    <height>600</height>
    <depth>3</depth>
  </size>
  <segmented>0</segmented>
  <object>
    <name>Hit</name>
    <pose>Unspecified</pose>
    <truncated>0</truncated>
    <difficult>0</difficult>
    <bndbox>
      <xmin>230.98</xmin>
      <ymin>466.98</ymin>
      <xmax>237.02</xmax>
      <ymax>237.02</ymax>
    </bndbox>
  </object>
  <object>
    <name>Hit</name>
    <pose>Unspecified</pose>
    <truncated>0</truncated>
    <difficult>0</difficult>
    <bndbox>
      <xmin>228.68</xmin>
      <ymin>509.68</ymin>
      <xmax>237.32</xmax>
      <ymax>237.32</ymax>
    </bndbox>
  </object>
  <object>
    <name>Hit</name>
    <pose>Unspecified</pose>
    <truncated>0</truncated>
    <difficult>0</difficult>
    <bndbox>
      <xmin>508.35</xmin>
      <ymin>304.35</ymin>
      <xmax>509.65</xmax>
      <ymax>509.65</ymax>
    </bndbox>
  </object>
  <object>
    <name>Hit</name>
    <pose>Unspecified</pose>
    <truncated>0</truncated>
    <difficult>0</difficult>
    <bndbox>
      <xmin>238.39</xmin>
      <ymin>458.39</ymin>
      <xmax>243.61</xmax>
      <ymax>243.61</ymax>
    </bndbox>
  </object>
  <object>
    <name>Hit</name>
    <pose>Unspecified</pose>
    <truncated>0</truncated>
    <difficult>0</difficult>
    <bndbox>
      <xmin>517.99</xmin>
      <ymin>280.99</ymin>
      <xmax>518.01</xmax>
      <ymax>518.01</ymax>
    </bndbox>
  </object>
  <object>
    <name>Hit</name>
    <pose>Unspecified</pose>
    <truncated>0</truncated>
    <difficult>0</difficult>
    <bndbox>
      <xmin>309.06</xmin>
      <ymin>555.06</ymin>
      <xmax>320.94</xmax>
      <ymax>320.94</ymax>
    </bndbox>
  </object>
  <object>
    <name>Hit</name>
    <pose>Unspecified</pose>
    <truncated>0</truncated>
    <difficult>0</difficult>
    <bndbox>
      <xmin>522.3</xmin>
      <ymin>318.3</ymin>
      <xmax>533.7</xmax>
      <ymax>533.7</ymax>
    </bndbox>
  </object>
  <object>
    <name>Hit</name>
    <pose>Unspecified</pose>
    <truncated>0</truncated>
    <difficult>0</difficult>
    <bndbox>
      <xmin>3.26</xmin>
      <ymin>340.26</ymin>
      <xmax>12.74</xmax>
      <ymax>12.74</ymax>
    </bndbox>
  </object>
  <object>
    <name>Hit</name>
    <pose>Unspecified</pose>
    <truncated>0</truncated>
    <difficult>0</difficult>
    <bndbox>
      <xmin>204.54</xmin>
      <ymin>137.54</ymin>
      <xmax>209.46</xmax>
      <ymax>209.46</ymax>
    </bndbox>
  </object>
</annotation>
