<annotation verified="yes">
  <folder>images</folder>
  <filename>hit_000175.png</filename>
  <path>C:\Users\Bence\Diplomamunka\YOLO3\test\kettes</path>
  <source>
    <database>Generator script</database>
  </source>
  <size>
    <width>600</width>
    <height>600</height>
    <depth>3</depth>
  </size>
  <segmented>0</segmented>
  <object>
    <name>Hit</name>
    <pose>Unspecified</pose>
    <truncated>0</truncated>
    <difficult>0</difficult>
    <bndbox>
      <xmin>236.73</xmin>
      <ymin>49.73</ymin>
      <xmax>243.27</xmax>
      <ymax>243.27</ymax>
    </bndbox>
  </object>
  <object>
    <name>Hit</name>
    <pose>Unspecified</pose>
    <truncated>0</truncated>
    <difficult>0</difficult>
    <bndbox>
      <xmin>513.47</xmin>
      <ymin>198.47</ymin>
      <xmax>514.53</xmax>
      <ymax>514.53</ymax>
    </bndbox>
  </object>
  <object>
    <name>Hit</name>
    <pose>Unspecified</pose>
    <truncated>0</truncated>
    <difficult>0</difficult>
    <bndbox>
      <xmin>261.5</xmin>
      <ymin>74.5</ymin>
      <xmax>264.5</xmax>
      <ymax>264.5</ymax>
    </bndbox>
  </object>
  <object>
    <name>Hit</name>
    <pose>Unspecified</pose>
    <truncated>0</truncated>
    <difficult>0</difficult>
    <bndbox>
      <xmin>462.95</xmin>
      <ymin>27.95</ymin>
      <xmax>471.05</xmax>
      <ymax>471.05</ymax>
    </bndbox>
  </object>
  <object>
    <name>Hit</name>
    <pose>Unspecified</pose>
    <truncated>0</truncated>
    <difficult>0</difficult>
    <bndbox>
      <xmin>273.17</xmin>
      <ymin>177.17</ymin>
      <xmax>288.83</xmax>
      <ymax>288.83</ymax>
    </bndbox>
  </object>
  <object>
    <name>Hit</name>
    <pose>Unspecified</pose>
    <truncated>0</truncated>
    <difficult>0</difficult>
    <bndbox>
      <xmin>309.83</xmin>
      <ymin>189.83</ymin>
      <xmax>310.17</xmax>
      <ymax>310.17</ymax>
    </bndbox>
  </object>
  <object>
    <name>Hit</name>
    <pose>Unspecified</pose>
    <truncated>0</truncated>
    <difficult>0</difficult>
    <bndbox>
      <xmin>498.67</xmin>
      <ymin>567.67</ymin>
      <xmax>505.33</xmax>
      <ymax>505.33</ymax>
    </bndbox>
  </object>
  <object>
    <name>Hit</name>
    <pose>Unspecified</pose>
    <truncated>0</truncated>
    <difficult>0</difficult>
    <bndbox>
      <xmin>352.46</xmin>
      <ymin>206.46</ymin>
      <xmax>363.54</xmax>
      <ymax>363.54</ymax>
    </bndbox>
  </object>
  <object>
    <name>Hit</name>
    <pose>Unspecified</pose>
    <truncated>0</truncated>
    <difficult>0</difficult>
    <bndbox>
      <xmin>475.73</xmin>
      <ymin>351.73</ymin>
      <xmax>478.27</xmax>
      <ymax>478.27</ymax>
    </bndbox>
  </object>
  <object>
    <name>Hit</name>
    <pose>Unspecified</pose>
    <truncated>0</truncated>
    <difficult>0</difficult>
    <bndbox>
      <xmin>109.01</xmin>
      <ymin>542.01</ymin>
      <xmax>112.99</xmax>
      <ymax>112.99</ymax>
    </bndbox>
  </object>
  <object>
    <name>Hit</name>
    <pose>Unspecified</pose>
    <truncated>0</truncated>
    <difficult>0</difficult>
    <bndbox>
      <xmin>575.32</xmin>
      <ymin>38.32</ymin>
      <xmax>588.68</xmax>
      <ymax>588.68</ymax>
    </bndbox>
  </object>
  <object>
    <name>Hit</name>
    <pose>Unspecified</pose>
    <truncated>0</truncated>
    <difficult>0</difficult>
    <bndbox>
      <xmin>31.33</xmin>
      <ymin>193.33</ymin>
      <xmax>40.67</xmax>
      <ymax>40.67</ymax>
    </bndbox>
  </object>
  <object>
    <name>Hit</name>
    <pose>Unspecified</pose>
    <truncated>0</truncated>
    <difficult>0</difficult>
    <bndbox>
      <xmin>368.28</xmin>
      <ymin>526.28</ymin>
      <xmax>377.72</xmax>
      <ymax>377.72</ymax>
    </bndbox>
  </object>
  <object>
    <name>Hit</name>
    <pose>Unspecified</pose>
    <truncated>0</truncated>
    <difficult>0</difficult>
    <bndbox>
      <xmin>271.88</xmin>
      <ymin>322.88</ymin>
      <xmax>274.12</xmax>
      <ymax>274.12</ymax>
    </bndbox>
  </object>
  <object>
    <name>Hit</name>
    <pose>Unspecified</pose>
    <truncated>0</truncated>
    <difficult>0</difficult>
    <bndbox>
      <xmin>555.95</xmin>
      <ymin>462.95</ymin>
      <xmax>576.05</xmax>
      <ymax>576.05</ymax>
    </bndbox>
  </object>
</annotation>
